{"is_source_file": true, "format": "Java", "description": "This file contains security configuration for a Spring Boot application, setting up HTTP security rules and password encoding.", "external_files": ["org.springframework.context.annotation.Bean", "org.springframework.context.annotation.Configuration", "org.springframework.security.config.Customizer", "org.springframework.security.config.annotation.web.builders.HttpSecurity", "org.springframework.security.crypto.bcrypt.BCryptPasswordEncoder", "org.springframework.security.web.SecurityFilterChain"], "external_methods": ["http.csrf()", "csrf.disable()", "authorizeHttpRequests()", "requestMatchers()", "permitAll()", "httpBasic()", "build()", "new BCryptPasswordEncoder()"], "published": ["securityFilterChain", "passwordEncoder"], "classes": [{"name": "SecurityConfig", "description": "Configuration class for setting up web security parameters in a Spring Boot application."}], "methods": [{"name": "securityFilterChain", "description": "Defines the security filter chain, disabling CSRF, setting request matchers with permitAll, and enabling HTTP Basic authentication."}, {"name": "passwordEncoder", "description": "Provides a BCrypt password encoder bean for hashing passwords."}], "calls": ["http.csrf()", "csrf.disable()", "authorizeHttpRequests()", "requestMatchers()", "permitAll()", "httpBasic()", "build()", "new BCryptPasswordEncoder()"], "search-terms": ["SecurityConfig", "HttpSecurity", "csrf", "permitAll", "BCryptPasswordEncoder", "securityFilterChain", "Spring Security configuration"], "state": 2, "file_id": 26, "knowledge_revision": 57, "git_revision": "b0d1b68860e8b1ca944d5afb36849369fabfc74b", "hash": "520dd6626b07a0968950bed697cc0bc8", "format-version": 4, "code-base-name": "recipe_backend", "filename": "recipe_backend/src/main/java/com/example/recipebackend/config/SecurityConfig.java", "revision_history": [{"57": "b0d1b68860e8b1ca944d5afb36849369fabfc74b"}]}